pgsql_test/__init__.py
pgsql_test/admin.py
pgsql_test/client.py
pgsql_test/connect.py
pgsql_test/manager.py
pgsql_test/seed/__init__.py
pgsql_test/seed/adapters.py
pgsql_test/seed/pgpm.py
pgsql_test/seed/sql.py
pgsql_test/types.py
pgsql_test-0.2.0.dist-info/METADATA
pgsql_test-0.2.0.dist-info/WHEEL
pgsql_test-0.2.0.dist-info/RECORD
