Metadata-Version: 2.4
Name: pgsql-test
Version: 0.2.0
Summary: PostgreSQL testing framework for Python - instant, isolated databases with automatic transaction rollback
License: MIT
Keywords: postgres,postgresql,testing,pytest,database,integration-tests
Author: Constructive
Author-email: developers@constructive.io
Requires-Python: >=3.10,<4.0
Classifier: Development Status :: 4 - Beta
Classifier: Environment :: Console
Classifier: Framework :: Pytest
Classifier: Intended Audience :: Developers
Classifier: License :: OSI Approved :: MIT License
Classifier: Operating System :: OS Independent
Classifier: Programming Language :: Python :: 3
Classifier: Programming Language :: Python :: 3.10
Classifier: Programming Language :: Python :: 3.11
Classifier: Programming Language :: Python :: 3.12
Classifier: Programming Language :: Python :: 3.13
Classifier: Programming Language :: Python :: 3.14
Classifier: Topic :: Database
Classifier: Topic :: Software Development :: Testing
Requires-Dist: psycopg2-binary (>=2.9,<3.0)
Project-URL: Homepage, https://github.com/constructive-io/pgsql-test-python
Project-URL: Repository, https://github.com/constructive-io/pgsql-test-python
